{ "frames": {
   "0": {
    "frame": { "x": 35, "y": 1, "w": 15, "h": 18 },
    "rotated": false,
    "trimmed": true,
    "spriteSourceSize": { "x": 1, "y": 0, "w": 13, "h": 16 },
    "sourceSize": { "w": 16, "h": 16 },
    "duration": 100
   },
   "1": {
    "frame": { "x": 51, "y": 1, "w": 15, "h": 18 },
    "rotated": false,
    "trimmed": true,
    "spriteSourceSize": { "x": 1, "y": 0, "w": 13, "h": 16 },
    "sourceSize": { "w": 16, "h": 16 },
    "duration": 100
   },
   "2": {
    "frame": { "x": 1, "y": 19, "w": 15, "h": 17 },
    "rotated": false,
    "trimmed": true,
    "spriteSourceSize": { "x": 1, "y": 1, "w": 13, "h": 15 },
    "sourceSize": { "w": 16, "h": 16 },
    "duration": 100
   },
   "3": {
    "frame": { "x": 1, "y": 1, "w": 16, "h": 17 },
    "rotated": false,
    "trimmed": true,
    "spriteSourceSize": { "x": 1, "y": 1, "w": 14, "h": 15 },
    "sourceSize": { "w": 16, "h": 16 },
    "duration": 100
   },
   "4": {
    "frame": { "x": 17, "y": 19, "w": 15, "h": 17 },
    "rotated": false,
    "trimmed": true,
    "spriteSourceSize": { "x": 1, "y": 1, "w": 13, "h": 15 },
    "sourceSize": { "w": 16, "h": 16 },
    "duration": 100
   },
   "5": {
    "frame": { "x": 1, "y": 37, "w": 14, "h": 15 },
    "rotated": false,
    "trimmed": true,
    "spriteSourceSize": { "x": 2, "y": 3, "w": 12, "h": 13 },
    "sourceSize": { "w": 16, "h": 16 },
    "duration": 50
   },
   "6": {
    "frame": { "x": 16, "y": 37, "w": 15, "h": 14 },
    "rotated": false,
    "trimmed": true,
    "spriteSourceSize": { "x": 2, "y": 0, "w": 13, "h": 12 },
    "sourceSize": { "w": 16, "h": 16 },
    "duration": 50
   },
   "7": {
    "frame": { "x": 16, "y": 37, "w": 15, "h": 14 },
    "rotated": false,
    "trimmed": true,
    "spriteSourceSize": { "x": 2, "y": 0, "w": 13, "h": 12 },
    "sourceSize": { "w": 16, "h": 16 },
    "duration": 50
   },
   "8": {
    "frame": { "x": 16, "y": 37, "w": 15, "h": 14 },
    "rotated": false,
    "trimmed": true,
    "spriteSourceSize": { "x": 2, "y": 0, "w": 13, "h": 12 },
    "sourceSize": { "w": 16, "h": 16 },
    "duration": 50
   },
   "9": {
    "frame": { "x": 18, "y": 1, "w": 16, "h": 17 },
    "rotated": false,
    "trimmed": true,
    "spriteSourceSize": { "x": 1, "y": 0, "w": 14, "h": 15 },
    "sourceSize": { "w": 16, "h": 16 },
    "duration": 75
   },
   "10": {
    "frame": { "x": 35, "y": 1, "w": 15, "h": 18 },
    "rotated": false,
    "trimmed": true,
    "spriteSourceSize": { "x": 1, "y": 0, "w": 13, "h": 16 },
    "sourceSize": { "w": 16, "h": 16 },
    "duration": 50
   },
   "11": {
    "frame": { "x": 32, "y": 48, "w": 14, "h": 15 },
    "rotated": false,
    "trimmed": true,
    "spriteSourceSize": { "x": 2, "y": 3, "w": 12, "h": 13 },
    "sourceSize": { "w": 16, "h": 16 },
    "duration": 50
   },
   "12": {
    "frame": { "x": 33, "y": 20, "w": 18, "h": 13 },
    "rotated": false,
    "trimmed": true,
    "spriteSourceSize": { "x": 0, "y": 5, "w": 16, "h": 11 },
    "sourceSize": { "w": 16, "h": 16 },
    "duration": 200
   },
   "13": {
    "frame": { "x": 52, "y": 20, "w": 18, "h": 13 },
    "rotated": false,
    "trimmed": true,
    "spriteSourceSize": { "x": 0, "y": 5, "w": 16, "h": 11 },
    "sourceSize": { "w": 16, "h": 16 },
    "duration": 200
   },
   "14": {
    "frame": { "x": 33, "y": 34, "w": 18, "h": 13 },
    "rotated": false,
    "trimmed": true,
    "spriteSourceSize": { "x": 0, "y": 5, "w": 16, "h": 11 },
    "sourceSize": { "w": 16, "h": 16 },
    "duration": 200
   },
   "15": {
    "frame": { "x": 52, "y": 34, "w": 18, "h": 13 },
    "rotated": false,
    "trimmed": true,
    "spriteSourceSize": { "x": 0, "y": 5, "w": 16, "h": 11 },
    "sourceSize": { "w": 16, "h": 16 },
    "duration": 200
   }
 },
 "meta": {
  "app": "http://www.aseprite.org/",
  "version": "1.2.25",
  "image": "bunny.png",
  "format": "RGBA8888",
  "size": { "w": 70, "h": 63 },
  "scale": "1",
  "frameTags": [
   { "name": "Idle", "from": 0, "to": 4, "direction": "forward" },
   { "name": "Walk", "from": 5, "to": 11, "direction": "forward" },
   { "name": "Sleep", "from": 12, "to": 15, "direction": "pingpong" }
  ],
  "layers": [
   { "name": "Layer 1", "opacity": 255, "blendMode": "normal" }
  ],
  "slices": [
  ]
 }
}
